configs/__init__.py
configs/constants.py
configs/env.py
handlers/__init__.py
resources/__init__.py
tests/__init__.py
tests/E2E_tests/__init__.py
tests/E2E_tests/cached_sessions_store_handler.py
utils/__init__.py
utils/exceptions.py
utils/jinja_utils.py
utils/logger.py
utils/network.py
utils/open_ai/__init__.py
utils/open_ai/common.py
utils/open_ai/completion_3_5.py
utils/open_ai/completion_4.py
opencopilot-0.0.1.dist-info/METADATA
opencopilot-0.0.1.dist-info/WHEEL
opencopilot-0.0.1.dist-info/top_level.txt
opencopilot-0.0.1.dist-info/RECORD
