Metadata-Version: 2.1
Name: opencopilot
Version: 0.0.1
Summary: An AI-driven Copilot Agent designed to offer an efficient and controllable framework for software companies
Home-page: https://github.com/Incorta/OpenCopilot
Author: Incorta
Author-email: devteam-python-libs@incorta.com
Requires-Python: >=3.6
Requires-Dist: openai (~=0.27.6)
Requires-Dist: termcolor (~=2.3.0)
Requires-Dist: jinja2 (~=3.1.2)
Requires-Dist: pydantic (~=1.10.7)
Requires-Dist: utils (~=1.0.1)
Requires-Dist: pytest (~=7.3.1)
